odakb/__init__.py
odakb/board.py
odakb/cli.py
odakb/config.py
odakb/cwl.py
odakb/datalake.py
odakb/evaluator.py
odakb/sparql.py
odakb/conf/defaults.yaml
odakb/conf/graphs.d/rdfservice-loaders.ttl
odakb/conf/graphs.d/spiacsonline.ttl
odakb/plugins/__init__.py
odakb/plugins/cc.py
odakb/templates/images.html
odakb/templates/index.html
odakb/vendor/bootstrap/js/bootstrap.bundle.js
odakb/vendor/bootstrap/js/bootstrap.bundle.js.map
odakb/vendor/bootstrap/js/bootstrap.bundle.min.js
odakb/vendor/bootstrap/js/bootstrap.bundle.min.js.map
odakb/vendor/bootstrap/js/bootstrap.js
odakb/vendor/bootstrap/js/bootstrap.js.map
odakb/vendor/bootstrap/js/bootstrap.min.js
odakb/vendor/bootstrap/js/bootstrap.min.js.map
odakb/vendor/bootstrap/scss/_alert.scss
odakb/vendor/bootstrap/scss/_badge.scss
odakb/vendor/bootstrap/scss/_breadcrumb.scss
odakb/vendor/bootstrap/scss/_button-group.scss
odakb/vendor/bootstrap/scss/_buttons.scss
odakb/vendor/bootstrap/scss/_card.scss
odakb/vendor/bootstrap/scss/_carousel.scss
odakb/vendor/bootstrap/scss/_close.scss
odakb/vendor/bootstrap/scss/_code.scss
odakb/vendor/bootstrap/scss/_custom-forms.scss
odakb/vendor/bootstrap/scss/_dropdown.scss
odakb/vendor/bootstrap/scss/_forms.scss
odakb/vendor/bootstrap/scss/_functions.scss
odakb/vendor/bootstrap/scss/_grid.scss
odakb/vendor/bootstrap/scss/_images.scss
odakb/vendor/bootstrap/scss/_input-group.scss
odakb/vendor/bootstrap/scss/_jumbotron.scss
odakb/vendor/bootstrap/scss/_list-group.scss
odakb/vendor/bootstrap/scss/_media.scss
odakb/vendor/bootstrap/scss/_mixins.scss
odakb/vendor/bootstrap/scss/_modal.scss
odakb/vendor/bootstrap/scss/_nav.scss
odakb/vendor/bootstrap/scss/_navbar.scss
odakb/vendor/bootstrap/scss/_pagination.scss
odakb/vendor/bootstrap/scss/_popover.scss
odakb/vendor/bootstrap/scss/_print.scss
odakb/vendor/bootstrap/scss/_progress.scss
odakb/vendor/bootstrap/scss/_reboot.scss
odakb/vendor/bootstrap/scss/_root.scss
odakb/vendor/bootstrap/scss/_spinners.scss
oda_knowledge_base-0.7.28.dist-info/COPYING
oda_knowledge_base-0.7.28.dist-info/METADATA
oda_knowledge_base-0.7.28.dist-info/WHEEL
oda_knowledge_base-0.7.28.dist-info/entry_points.txt
oda_knowledge_base-0.7.28.dist-info/top_level.txt
oda_knowledge_base-0.7.28.dist-info/RECORD
